AUTHORS.md
LICENSE
MANIFEST.in
README.md
setup.py
climetlab_script_web/.gitignore
climetlab_script_web/__init__.py
climetlab_script_web/app.py
climetlab_script_web/version
climetlab_script_web.egg-info/PKG-INFO
climetlab_script_web.egg-info/SOURCES.txt
climetlab_script_web.egg-info/dependency_links.txt
climetlab_script_web.egg-info/entry_points.txt
climetlab_script_web.egg-info/requires.txt
climetlab_script_web.egg-info/top_level.txt
climetlab_script_web.egg-info/zip-safe
climetlab_script_web/build/asset-manifest.json
climetlab_script_web/build/favicon.ico
climetlab_script_web/build/index.html
climetlab_script_web/build/logo192.png
climetlab_script_web/build/logo512.png
climetlab_script_web/build/manifest.json
climetlab_script_web/build/robots.txt
climetlab_script_web/build/static/js/main.33c10c35.js
climetlab_script_web/build/static/js/main.33c10c35.js.LICENSE.txt
climetlab_script_web/build/static/js/main.33c10c35.js.map